zaowr_polsl_kisiel/__init__.py
zaowr_polsl_kisiel/calibration/__init__.py
zaowr_polsl_kisiel/calibration/calibrate_camera.py
zaowr_polsl_kisiel/calibration/stereo_calibration.py
zaowr_polsl_kisiel/content_loaders/__init__.py
zaowr_polsl_kisiel/content_loaders/are_params_valid.py
zaowr_polsl_kisiel/content_loaders/load_calibration.py
zaowr_polsl_kisiel/content_loaders/load_depth_map_calibration.py
zaowr_polsl_kisiel/content_loaders/load_pfm_file.py
zaowr_polsl_kisiel/content_loaders/load_pgm_file.py
zaowr_polsl_kisiel/content_loaders/load_rectification_maps.py
zaowr_polsl_kisiel/content_loaders/load_stereo_calibration.py
zaowr_polsl_kisiel/content_loaders/save_calibration.py
zaowr_polsl_kisiel/content_loaders/save_disparity_map.py
zaowr_polsl_kisiel/content_loaders/write_ply_file.py
zaowr_polsl_kisiel/custom_exceptions/__init__.py
zaowr_polsl_kisiel/custom_exceptions/exceptions.py
zaowr_polsl_kisiel/image_processing/__init__.py
zaowr_polsl_kisiel/image_processing/calculate_color_difference_map.py
zaowr_polsl_kisiel/image_processing/calculate_disparity_map.py
zaowr_polsl_kisiel/image_processing/create_color_point_cloud.py
zaowr_polsl_kisiel/image_processing/decode_depth_map.py
zaowr_polsl_kisiel/image_processing/depth_map_normalize.py
zaowr_polsl_kisiel/image_processing/depth_to_disparity_map.py
zaowr_polsl_kisiel/image_processing/disparity_map_normalize.py
zaowr_polsl_kisiel/image_processing/disparity_to_depth_map.py
zaowr_polsl_kisiel/image_processing/remove_distortion.py
zaowr_polsl_kisiel/image_processing/stereo_rectify.py
zaowr_polsl_kisiel/optical_flow/__init__.py
zaowr_polsl_kisiel/optical_flow/dense_optical_flow.py
zaowr_polsl_kisiel/optical_flow/list_camera_ports_available.py
zaowr_polsl_kisiel/optical_flow/read_images_from_folder.py
zaowr_polsl_kisiel/optical_flow/sparse_optical_flow.py
zaowr_polsl_kisiel/tools/__init__.py
zaowr_polsl_kisiel/tools/calculate_mse_disparity.py
zaowr_polsl_kisiel/tools/calculate_ssim_disparity.py
zaowr_polsl_kisiel-0.0.32.dist-info/LICENSE
zaowr_polsl_kisiel-0.0.32.dist-info/METADATA
zaowr_polsl_kisiel-0.0.32.dist-info/WHEEL
zaowr_polsl_kisiel-0.0.32.dist-info/top_level.txt
zaowr_polsl_kisiel-0.0.32.dist-info/RECORD
