Metadata-Version: 2.2
Name: zaowr_polsl_kisiel
Version: 0.0.32
Summary: A simple Python package used by me and my friends at university in the 'Advanced Image, Video and Motion Analysis' course.
Author: Maksymilian Kisiel
License: Copyright (c) 2018 The Python Packaging Authority
Project-URL: Repository, https://github.com/revalew/zaowr-py-package
Project-URL: Issues, https://github.com/revalew/zaowr-py-package/issues
Project-URL: Changelog, https://github.com/revalew/zaowr-py-package/releases
Project-URL: Documentation, https://github.com/revalew/zaowr-py-package/blob/master/docs/USAGE.md
Keywords: polsl,zaowr,2024/2025,IGT,ZAOWR
Classifier: Programming Language :: Python :: 3
Classifier: License :: OSI Approved :: MIT License
Classifier: Operating System :: OS Independent
Requires-Python: >=3.8
License-File: LICENSE
Requires-Dist: opencv-python==4.10.0.84
Requires-Dist: numpy==2.1.3
Requires-Dist: tqdm==4.67.1
Requires-Dist: colorama==0.4.6
Requires-Dist: matplotlib==3.10.0
Requires-Dist: scikit-image==0.25.0
Requires-Dist: scikit-learn==1.6.1
Provides-Extra: dev
Requires-Dist: iniconfig==2.0.0; extra == "dev"
Requires-Dist: Jinja2==3.1.4; extra == "dev"
Requires-Dist: MarkupSafe==3.0.2; extra == "dev"
Requires-Dist: mypy==1.13.0; extra == "dev"
Requires-Dist: mypy-extensions==1.0.0; extra == "dev"
Requires-Dist: packaging==24.2; extra == "dev"
Requires-Dist: pdoc==15.0.0; extra == "dev"
Requires-Dist: pluggy==1.5.0; extra == "dev"
Requires-Dist: Pygments==2.18.0; extra == "dev"
Requires-Dist: pytest==8.3.3; extra == "dev"
Requires-Dist: pytest-mock==3.14.0; extra == "dev"
Requires-Dist: typing_extensions==4.12.2; extra == "dev"
